zafiaonline/__init__.py
zafiaonline/main.py
zafiaonline/main.pyi
zafiaonline/version.py
zafiaonline/api_client/__init__.py
zafiaonline/api_client/api_decorators.py
zafiaonline/api_client/global_chat_methods.py
zafiaonline/api_client/player_methods.py
zafiaonline/api_client/room_methods.py
zafiaonline/api_client/user_methods.py
zafiaonline/api_client/zafia_api.py
zafiaonline/api_client/https_api/__init__.py
zafiaonline/api_client/https_api/https_api.py
zafiaonline/api_client/https_api/https_api_helpers.py
zafiaonline/service_generator/__init__.py
zafiaonline/service_generator/helper.py
zafiaonline/structures/__init__.py
zafiaonline/structures/enums.py
zafiaonline/structures/models.py
zafiaonline/structures/packet_data_keys.py
zafiaonline/transport/__init__.py
zafiaonline/transport/http/__init.py
zafiaonline/transport/http/http_module.py
zafiaonline/transport/http/http_wrapper.py
zafiaonline/transport/websocket/__init__.py
zafiaonline/transport/websocket/config.py
zafiaonline/transport/websocket/websocket_handler.py
zafiaonline/transport/websocket/websocket_module.py
zafiaonline/transport/websocket/ws_config.yaml
zafiaonline/utils/__init__.py
zafiaonline/utils/exceptions.py
zafiaonline/utils/logging_config.py
zafiaonline/utils/md5hash.py
zafiaonline/utils/proxy_store.py
zafiaonline/utils/utils.py
zafiaonline/utils/utils_for_send_messages.py
zafiaonline-9.0.2.dist-info/METADATA
zafiaonline-9.0.2.dist-info/WHEEL
zafiaonline-9.0.2.dist-info/top_level.txt
zafiaonline-9.0.2.dist-info/RECORD
