Metadata-Version: 2.4
Name: zafiaonline
Version: 9.0.2
Summary: A Python API library for interacting with Mafia Online game.
Author: unelected
License-Expression: GPL-3.0-or-later
Project-URL: Homepage, https://github.com/unelected/zafiaonline.py
Project-URL: Repository, https://github.com/unelected/zafiaonline.py.git
Keywords: Mafia Online API,API Mafia Online
Classifier: Development Status :: 5 - Production/Stable
Classifier: Environment :: Console
Classifier: Intended Audience :: Developers
Requires-Python: >=3.10
Requires-Dist: websockets>=15.0.1
Requires-Dist: msgspec~=0.19
Requires-Dist: aiohttp~=3.12
Requires-Dist: pyyaml~=6.0
Requires-Dist: pytest~=8.4
